bcr_mcp3008
